colorxkat/__init__.py
colorxkat/colors.py
colorxkat/gradients.py
colorxkat/utils.py
kittycolors-1.0.0.dist-info/METADATA
kittycolors-1.0.0.dist-info/WHEEL
kittycolors-1.0.0.dist-info/top_level.txt
kittycolors-1.0.0.dist-info/RECORD
