Metadata-Version: 2.4
Name: kittycolors
Version: 1.0.0
Summary: color lib dats kewlio
Author: g4
Author-email: defnotg4@gmail.com
Requires-Python: >=3.6
Dynamic: author
Dynamic: author-email
Dynamic: requires-python
Dynamic: summary
